{
  "version": 1,
  "max_destinations": 2,
  "review_tags": [
    "review_required",
    "ambiguous"
  ],
  "skip_tags": [
    "skip_candidate"
  ],
  "rule_defaults": {
    "enabled": true,
    "minimum_score": 4,
    "priority": 0,
    "tag_penalties": {
      "skip_candidate": 8
    },
    "content_mode_adjustments": {
      "title_only": -1
    }
  },
  "channels": [
    {
      "channel_key": "africa",
      "priority": 90,
      "tag_boosts": {
        "africa": 5,
        "ghana": 7,
        "south_africa": 4,
        "ethiopia": 4,
        "nigeria": 4,
        "dr_congo": 4,
        "kenya": 4,
        "sudan": 4,
        "south_sudan": 5,
        "tunisia": 4,
        "namibia": 4,
        "malawi": 4,
        "burkina_faso": 4,
        "zambia": 4,
        "uganda": 4,
        "madagascar": 4,
        "congo": 4,
        "election": 1,
        "civil_unrest": 2,
        "humanitarian": 1,
        "economy": 1,
        "finance": 1,
        "diplomacy": 1
      },
      "tag_penalties": {
        "skip_candidate": 8,
        "north_america": 2,
        "latin_america": 2
      },
      "required_any": [
        "africa",
        "ghana",
        "south_africa",
        "ethiopia",
        "nigeria",
        "dr_congo",
        "kenya",
        "sudan",
        "south_sudan",
        "tunisia",
        "namibia",
        "malawi",
        "burkina_faso",
        "zambia",
        "uganda",
        "madagascar",
        "congo"
      ],
      "source_biases": {
        "Africa": 2,
        "Crisis Group": 1,
        "State Department Africa": 2
      },
      "destination_class": "primary"
    },
    {
      "channel_key": "europe",
      "priority": 90,
      "term_boosts": {
        "ukraine_war": 8,
        "nato": 1
      },
      "tag_boosts": {
        "europe": 5,
        "ukraine": 7,
        "russia": 5,
        "spain": 4,
        "italy": 4,
        "france": 4,
        "germany": 4,
        "sweden": 4,
        "slovenia": 4,
        "croatia": 4,
        "iceland": 4,
        "andorra": 4,
        "switzerland": 5,
        "united_kingdom": 4,
        "turkey": 4,
        "military": 3,
        "attack": 3,
        "missile": 3,
        "drone": 2,
        "diplomacy": 1,
        "economy": 1,
        "finance": 1
      },
      "required_any": [
        "europe",
        "ukraine",
        "russia",
        "spain",
        "italy",
        "france",
        "germany",
        "sweden",
        "slovenia",
        "croatia",
        "iceland",
        "andorra",
        "switzerland",
        "united_kingdom",
        "turkey"
      ],
      "source_biases": {
        "Europe": 2,
        "Ukraine": 2,
        "Kyiv Independent": 3
      },
      "minimum_score": 4,
      "notes": "Russia-Ukraine war signals should beat military domain buckets.",
      "destination_class": "primary"
    },
    {
      "channel_key": "indo-pacific",
      "priority": 90,
      "term_boosts": {
        "india_security_crisis": 3,
        "taiwan_strait": 2,
        "south_china_sea": 2,
        "philippine_sea": 2
      },
      "tag_boosts": {
        "indo_pacific": 5,
        "china": 6,
        "taiwan": 6,
        "japan": 4,
        "philippines": 5,
        "india": 4,
        "pakistan": 4,
        "australia": 4,
        "south_korea": 4,
        "north_korea": 5,
        "vietnam": 4,
        "myanmar": 5,
        "laos": 4,
        "brunei": 4,
        "timor_leste": 4,
        "marshall_islands": 4,
        "new_caledonia": 4,
        "naval": 2,
        "economy": 1,
        "finance": 1,
        "diplomacy": 1
      },
      "tag_penalties": {
        "india": 7
      },
      "required_any": [
        "indo_pacific",
        "china",
        "taiwan",
        "japan",
        "philippines",
        "india",
        "pakistan",
        "australia",
        "south_korea",
        "north_korea",
        "vietnam",
        "myanmar",
        "laos",
        "brunei",
        "timor_leste",
        "marshall_islands",
        "new_caledonia"
      ],
      "source_biases": {},
      "destination_class": "primary"
    },
    {
      "channel_key": "middle-east",
      "priority": 90,
      "term_boosts": {
        "iran_war": 9,
        "red_sea": 4,
        "strait_of_hormuz": 5,
        "bab_el_mandeb": 3,
        "centcom": 3
      },
      "tag_boosts": {
        "middle_east": 5,
        "iran": 6,
        "iraq": 5,
        "israel": 6,
        "lebanon": 5,
        "yemen": 5,
        "kuwait": 5,
        "bahrain": 5,
        "oman": 4,
        "saudi_arabia": 4,
        "uae": 4,
        "qatar": 4,
        "naval": 2,
        "military": 3,
        "attack": 3,
        "missile": 3,
        "drone": 2,
        "sanctions": 1,
        "economy": 1,
        "finance": 1,
        "diplomacy": 1
      },
      "required_any": [
        "middle_east",
        "iran",
        "iraq",
        "israel",
        "lebanon",
        "yemen",
        "kuwait",
        "bahrain",
        "oman",
        "saudi_arabia",
        "uae",
        "qatar",
        "red_sea",
        "strait_of_hormuz",
        "bab_el_mandeb",
        "centcom"
      ],
      "source_biases": {
        "CENTCOM": 3,
        "AlArabiya_Eng": 2,
        "Arab News": 2,
        "QNAEnglish": 2,
        "Middle East": 2,
        "Times of Israel": 2,
        "Iran": 2,
        "Near East": 2
      },
      "minimum_score": 4,
      "notes": "Middle East conflict and Gulf-state signals should beat military domain buckets.",
      "destination_class": "primary"
    },
    {
      "channel_key": "north-america",
      "minimum_score": 6,
      "priority": 45,
      "tag_boosts": {
        "united_states": 7,
        "canada": 5,
        "north_america": 2,
        "government": 1,
        "legislation": 1,
        "election": 1,
        "disaster": 1,
        "economy": 1,
        "finance": 1
      },
      "tag_penalties": {
        "latin_america": 7,
        "africa": 7,
        "middle_east": 6,
        "indo_pacific": 6,
        "europe": 6,
        "india": 8,
        "china": 5,
        "australia": 5,
        "government": 3,
        "legislation": 3,
        "election": 3
      },
      "required_any": [
        "united_states",
        "canada",
        "north_america"
      ],
      "source_biases": {
        "DVIDS": -4
      },
      "destination_class": "primary"
    },
    {
      "channel_key": "south-central-america",
      "minimum_score": 5,
      "priority": 70,
      "tag_boosts": {
        "latin_america": 6,
        "argentina": 4,
        "brazil": 4,
        "chile": 4,
        "colombia": 5,
        "cuba": 4,
        "ecuador": 4,
        "peru": 4,
        "bolivia": 4,
        "paraguay": 4,
        "uruguay": 4,
        "haiti": 4,
        "guatemala": 4,
        "honduras": 4,
        "el_salvador": 4,
        "nicaragua": 4,
        "costa_rica": 4,
        "dominican_republic": 4,
        "dominica": 4,
        "anguilla": 4,
        "antigua_barbuda": 4,
        "british_virgin_islands": 4,
        "cayman_islands": 4,
        "mexico": 4,
        "panama": 4,
        "venezuela": 4,
        "government": 1,
        "election": 2,
        "civil_unrest": 2,
        "humanitarian": 1,
        "economy": 1,
        "finance": 1,
        "diplomacy": 1
      },
      "tag_penalties": {
        "middle_east": 14,
        "indo_pacific": 14,
        "europe": 10,
        "africa": 8,
        "iran": 6,
        "israel": 6,
        "china": 6,
        "russia": 6,
        "ukraine": 6,
        "united_states": 4
      },
      "term_penalties": {
        "presidential_nominations": 8
      },
      "required_any": [
        "latin_america",
        "argentina",
        "brazil",
        "chile",
        "colombia",
        "cuba",
        "ecuador",
        "peru",
        "bolivia",
        "paraguay",
        "uruguay",
        "haiti",
        "guatemala",
        "honduras",
        "el_salvador",
        "nicaragua",
        "costa_rica",
        "dominican_republic",
        "dominica",
        "anguilla",
        "antigua_barbuda",
        "british_virgin_islands",
        "cayman_islands",
        "mexico",
        "panama",
        "venezuela"
      ],
      "source_biases": {
        "Latin America": 2,
        "Western Hemisphere": 2,
        "Americas": 2,
        "Miami Herald": 2,
        "NYT Americas": 2
      },
      "destination_class": "primary"
    },
    {
      "channel_key": "arctic",
      "minimum_score": 4,
      "priority": 88,
      "term_boosts": {
        "region_arctic": 3,
        "arctic_places": 4,
        "arctic_military_commands": 5,
        "northcom_norad": 2,
        "spacecom": 1
      },
      "tag_boosts": {
        "arctic": 8,
        "military": 2,
        "military_organization": 2,
        "maritime": 2,
        "naval": 2,
        "air": 1,
        "space": 1,
        "energy_security": 1
      },
      "tag_penalties": {
        "skip_candidate": 9,
        "middle_east": 4,
        "indo_pacific": 3,
        "latin_america": 6,
        "africa": 6
      },
      "required_any": [
        "arctic"
      ],
      "source_biases": {
        "Arctic": 3,
        "High North": 3,
        "NORTHCOM": 2,
        "NORAD": 2,
        "Coast Guard": 1
      },
      "notes": "Arctic / High North geography, security, energy, and military posture.",
      "destination_class": "primary"
    },
    {
      "channel_key": "sea",
      "priority": 100,
      "term_boosts": {
        "carrier_strike_group": 2,
        "chinese_aircraft_carrier": 2,
        "chinese_carrier": 2,
        "naval_warfare_terms": 2,
        "transcom": 1
      },
      "tag_boosts": {
        "naval": 6,
        "maritime": 1,
        "aircraft_carrier": 5,
        "carrier_strike_group": 6,
        "destroyer": 4,
        "submarine": 4,
        "military_movement": 2,
        "amphibious": 5,
        "military_sealift": 5,
        "naval_air_wing": 4,
        "maritime_patrol": 3,
        "coast_guard": 4,
        "military_logistics": 2
      },
      "tag_penalties": {
        "skip_candidate": 9,
        "middle_east": 8,
        "europe": 8,
        "iran": 6,
        "israel": 5,
        "lebanon": 5,
        "yemen": 5,
        "ukraine": 6,
        "russia": 6,
        "active_conflict": 12,
        "special_operations": 12,
        "government": 4,
        "election": 5,
        "economy": 4,
        "finance": 4,
        "civilian_technology": 3
      },
      "term_penalties": {
        "ukraine_war": 12,
        "iran_war": 12,
        "gaza_war": 5,
        "lebanon_conflict": 5,
        "strait_of_hormuz": 6,
        "civilian_cap_terms": 8,
        "election": 4,
        "economy_news": 4,
        "stock_market": 4
      },
      "required_any": [
        "naval",
        "aircraft_carrier",
        "carrier_strike_group",
        "destroyer",
        "submarine",
        "amphibious",
        "military_sealift",
        "naval_air_wing",
        "maritime_patrol",
        "coast_guard"
      ],
      "source_biases": {
        "Naval": 3,
        "USNI": 3,
        "Seapower": 3
      },
      "destination_class": "primary",
      "excluded_any": [
        "active_conflict",
        "special_operations"
      ]
    },
    {
      "channel_key": "air",
      "priority": 95,
      "term_boosts": {
        "drone": 1,
        "strategic_bomber": 1,
        "air_warfare_terms": 2,
        "command_control_terms": 1
      },
      "tag_boosts": {
        "air": 6,
        "fighter_aircraft": 5,
        "bomber_aircraft": 4,
        "strategic_bomber": 3,
        "drone": 4,
        "naval_air_wing": 3,
        "maritime_patrol": 4,
        "isr": 3,
        "electronic_warfare": 4,
        "command_control": 1
      },
      "tag_penalties": {
        "skip_candidate": 9,
        "air_defense": 6,
        "missile_defense": 5,
        "ground": 2,
        "middle_east": 8,
        "europe": 8,
        "iran": 6,
        "israel": 5,
        "lebanon": 5,
        "yemen": 5,
        "ukraine": 6,
        "russia": 6,
        "active_conflict": 12,
        "government": 5,
        "election": 6,
        "economy": 5,
        "finance": 5,
        "civilian_technology": 4
      },
      "term_penalties": {
        "ukraine_war": 12,
        "iran_war": 12,
        "gaza_war": 5,
        "lebanon_conflict": 5,
        "strait_of_hormuz": 6,
        "civilian_cap_terms": 12,
        "election": 4,
        "economy_news": 5,
        "stock_market": 5
      },
      "required_any": [
        "air",
        "fighter_aircraft",
        "bomber_aircraft",
        "strategic_bomber",
        "drone",
        "naval_air_wing",
        "maritime_patrol",
        "isr",
        "electronic_warfare"
      ],
      "source_biases": {
        "Air": 3,
        "FAA": -2,
        "Aerospace": 2
      },
      "destination_class": "primary",
      "excluded_any": [
        "active_conflict"
      ]
    },
    {
      "channel_key": "land",
      "priority": 95,
      "term_boosts": {
        "air_defense": 1,
        "missile_defense": 1,
        "land_warfare_terms": 2,
        "command_control_terms": 1
      },
      "tag_boosts": {
        "ground": 6,
        "air_defense": 7,
        "missile_defense": 6,
        "military": 2,
        "military_base": 2,
        "military_movement": 2,
        "exercise": 2,
        "marine_littoral": 5,
        "sustainment": 2,
        "command_control": 2,
        "counterterrorism": 2
      },
      "tag_penalties": {
        "skip_candidate": 9,
        "middle_east": 8,
        "europe": 8,
        "iran": 6,
        "israel": 5,
        "lebanon": 5,
        "yemen": 5,
        "ukraine": 6,
        "russia": 6,
        "active_conflict": 12,
        "government": 4,
        "election": 5,
        "economy": 4,
        "finance": 4,
        "civilian_technology": 3
      },
      "term_penalties": {
        "ukraine_war": 12,
        "iran_war": 12,
        "gaza_war": 5,
        "lebanon_conflict": 5,
        "strait_of_hormuz": 6,
        "civilian_cap_terms": 8,
        "election": 4,
        "economy_news": 4,
        "stock_market": 4
      },
      "required_any": [
        "ground",
        "air_defense",
        "missile_defense",
        "military_base",
        "military_movement",
        "exercise",
        "marine_littoral",
        "command_control"
      ],
      "source_biases": {
        "Land": 3,
        "Army": 2,
        "Military Times": 1
      },
      "destination_class": "primary",
      "excluded_any": [
        "active_conflict"
      ]
    },
    {
      "channel_key": "space",
      "priority": 95,
      "tag_boosts": {
        "space": 7,
        "military": 1,
        "company": 1,
        "missile_warning": 4,
        "intelligence": 2,
        "military_organization": 1
      },
      "required_any": [
        "space",
        "missile_warning",
        "intelligence",
        "military_organization"
      ],
      "source_biases": {
        "Space": 3
      },
      "destination_class": "primary",
      "term_boosts": {
        "spacecom": 3,
        "space_warfare_terms": 3,
        "stratcom": 1
      }
    },
    {
      "channel_key": "science-technology",
      "minimum_score": 7,
      "priority": 75,
      "term_boosts": {
        "artificial_intelligence": 2,
        "semiconductors": 2,
        "major_tech_companies": 0,
        "chip_companies": 2,
        "civilian_innovation": 1,
        "biotechnology": 1
      },
      "tag_boosts": {
        "technology": 3,
        "civilian_technology": 3,
        "science": 5,
        "artificial_intelligence": 7,
        "semiconductor": 7,
        "consumer_technology": 5,
        "civilian_innovation": 5,
        "biotechnology": 4,
        "cryptocurrency": 4,
        "cyber": 2
      },
      "tag_penalties": {
        "skip_candidate": 9,
        "military": 8,
        "defense_industry": 10,
        "procurement": 8,
        "military_organization": 6,
        "attack": 4,
        "drone": 5,
        "missile": 5,
        "air_defense": 5,
        "missile_defense": 5,
        "strategic_weapon": 8,
        "nuclear_weapon": 8,
        "middle_east": 10,
        "europe": 10,
        "indo_pacific": 2,
        "economy": 3,
        "finance": 3,
        "stock_market": 4,
        "investing": 4,
        "earnings": 4,
        "iran": 6,
        "ukraine": 6,
        "russia": 6
      },
      "term_penalties": {
        "ukraine_war": 12,
        "iran_war": 12,
        "gaza_war": 6,
        "lebanon_conflict": 6,
        "defense_industry": 8,
        "military_technology": 12,
        "air_defense": 5,
        "missile_defense": 5,
        "carrier_strike_group": 5,
        "strait_of_hormuz": 6,
        "major_tech_companies": 3
      },
      "required_any": [
        "technology",
        "civilian_technology",
        "science",
        "artificial_intelligence",
        "semiconductor",
        "consumer_technology",
        "civilian_innovation",
        "biotechnology",
        "cryptocurrency"
      ],
      "source_biases": {
        "Technology": 3,
        "Science": 2,
        "Bluesky: Sheera Frenkel": 3,
        "Bluesky: Renee Dudley": 3,
        "Bluesky: Sean Lyngaas": 3,
        "Bluesky: Rishi Iyengar": 3,
        "Bluesky: Catalin Cimpanu": 4,
        "Bluesky: Mia Sato": 3,
        "Bluesky: Daryna Antoniuk": 4,
        "Bluesky: Mathew J Schwartz": 4,
        "Bluesky: Andy Greenberg": 4,
        "Bluesky: Kim Zetter": 4,
        "Bluesky: Lorenzo Franceschi-Bicchierai": 4,
        "Bluesky: Tim Fernholz": 3
      },
      "destination_class": "primary"
    },
    {
      "channel_key": "special-operations",
      "minimum_score": 5,
      "priority": 85,
      "tag_boosts": {
        "special_operations": 10,
        "military_organization": 1,
        "counterterrorism": 3
      },
      "tag_penalties": {
        "skip_candidate": 9,
        "cyber": 5,
        "indo_pacific": 6,
        "north_korea": 4,
        "china": 4,
        "middle_east": 8,
        "europe": 8,
        "iran": 6,
        "israel": 4,
        "lebanon": 4,
        "yemen": 4,
        "ukraine": 6,
        "russia": 6
      },
      "term_penalties": {
        "ukraine_war": 12,
        "iran_war": 12,
        "gaza_war": 8,
        "lebanon_conflict": 8,
        "centcom": 3,
        "strait_of_hormuz": 6,
        "bab_el_mandeb": 3
      },
      "required_any": [
        "special_operations"
      ],
      "source_biases": {
        "Task & Purpose": 2,
        "War Zone": 2,
        "Counterterrorism": 2
      },
      "destination_class": "primary",
      "term_boosts": {
        "socom": 4,
        "counterterrorism": 1
      }
    },
    {
      "channel_key": "training-and-doctrine",
      "minimum_score": 5,
      "priority": 80,
      "tag_boosts": {
        "exercise": 4,
        "military": 3,
        "military_organization": 2,
        "procurement": 1,
        "command_control": 3,
        "military_logistics": 2
      },
      "tag_penalties": {
        "skip_candidate": 9,
        "cyber": 5,
        "indo_pacific": 6,
        "north_korea": 4,
        "china": 4,
        "middle_east": 8,
        "europe": 8,
        "iran": 6,
        "israel": 4,
        "lebanon": 4,
        "yemen": 4,
        "ukraine": 6,
        "russia": 6
      },
      "term_penalties": {
        "ukraine_war": 12,
        "iran_war": 12,
        "gaza_war": 8,
        "lebanon_conflict": 8,
        "centcom": 3,
        "strait_of_hormuz": 6
      },
      "required_any": [
        "exercise",
        "military",
        "command_control",
        "military_logistics"
      ],
      "source_biases": {
        "War on the Rocks": 2,
        "Modern War Institute": 2,
        "War College": 2,
        "Training": 2
      },
      "destination_class": "primary"
    },
    {
      "channel_key": "strategic-weapons",
      "minimum_score": 6,
      "priority": 90,
      "term_boosts": {
        "nuclear_weapons": 2,
        "nuclear_deterrence": 2,
        "icbm": 2,
        "slbm": 2,
        "strategic_bomber": 1,
        "hypersonic_weapon": 1,
        "arms_control": 1,
        "stratcom": 3,
        "space_warfare_terms": 1
      },
      "tag_boosts": {
        "nuclear_weapon": 8,
        "nuclear_deterrence": 7,
        "icbm": 8,
        "slbm": 8,
        "strategic_bomber": 6,
        "strategic_weapon": 5,
        "hypersonic_weapon": 5,
        "arms_control": 5,
        "missile_warning": 5,
        "command_control": 2
      },
      "tag_penalties": {
        "skip_candidate": 9,
        "air_defense": 8,
        "missile_defense": 8,
        "drone": 4,
        "fighter_aircraft": 4,
        "ground": 3
      },
      "required_any": [
        "nuclear_weapon",
        "nuclear_deterrence",
        "icbm",
        "slbm",
        "strategic_bomber",
        "strategic_weapon",
        "hypersonic_weapon",
        "arms_control",
        "missile_warning"
      ],
      "source_biases": {
        "Arms Control": 3,
        "SIPRI": 2
      },
      "destination_class": "primary"
    },
    {
      "channel_key": "industrial-base",
      "priority": 90,
      "term_boosts": {
        "defense_industry": 2,
        "defense_contracts": 2,
        "defense_production_stockpiles": 2,
        "military_technology": 1
      },
      "tag_boosts": {
        "defense_industry": 8,
        "procurement": 7,
        "legislation": 1,
        "military": 1,
        "production": 5,
        "stockpile": 5,
        "military_logistics": 3,
        "command_control": 1
      },
      "tag_penalties": {
        "skip_candidate": 9,
        "indo_pacific": 4,
        "north_korea": 3,
        "china": 3,
        "lebanon": 3,
        "yemen": 3
      },
      "term_penalties": {},
      "required_any": [
        "defense_industry",
        "procurement"
      ],
      "source_biases": {
        "Defense News Industry": 3,
        "DefenseScoop": 3,
        "Contracts": 3,
        "BreakingDefense": 2,
        "defense_news": 2,
        "Lockheed": 2,
        "RTX": 2,
        "Northrop": 2,
        "Anduril": 2,
        "BoeingDefense": 2
      },
      "minimum_score": 6,
      "notes": "Defense procurement, contracts, production, stockpiles, acquisition, and industrial capacity.",
      "destination_class": "primary"
    },
    {
      "channel_key": "natsec-news",
      "minimum_score": 7,
      "priority": 55,
      "term_boosts": {
        "national_security": 2,
        "intelligence_community": 2,
        "homeland_security": 2,
        "counterterrorism": 2,
        "combatant_commands": 1,
        "cybercom": 2,
        "socom": 2,
        "command_control_terms": 1
      },
      "tag_boosts": {
        "national_security": 5,
        "intelligence": 5,
        "homeland_security": 4,
        "counterterrorism": 5,
        "military_organization": 2,
        "command_control": 2,
        "isr": 2,
        "cyber": 2
      },
      "tag_penalties": {
        "skip_candidate": 9,
        "election": 5,
        "stock_market": 6,
        "investing": 6,
        "earnings": 6
      },
      "required_any": [
        "national_security",
        "intelligence",
        "homeland_security",
        "counterterrorism",
        "command_control",
        "isr"
      ],
      "required_source_ids": [
        "x-natsec-news"
      ],
      "source_biases": {
        "NatSec": 4,
        "National Security": 3,
        "Lawfare": 2,
        "Just Security": 2,
        "War on the Rocks": 2
      },
      "notes": "Dedicated NatSec_News X account destination. Hard-gated to source_id x-natsec-news.",
      "destination_class": "primary"
    },
    {
      "channel_key": "wire-service",
      "minimum_score": 6,
      "priority": 20,
      "tag_boosts": {},
      "source_biases": {
        "Top Stories": 2,
        "BBC": 2,
        "Google News": 2,
        "Bluesky: CNN": 3,
        "Bluesky: Axios": 3,
        "Bluesky: Financial Times": 2,
        "Bluesky: Bloomberg": 2,
        "Bluesky: The Guardian": 2,
        "Bluesky: Boston Globe": 2,
        "Bluesky: SCOTUSblog": 2,
        "Bluesky: AFP Fact Check": 2,
        "Bluesky: Meduza English": 2,
        "Bluesky: ProPublica": 2,
        "Bluesky: Semafor": 2,
        "Bluesky: The Atlantic": 2,
        "Bluesky: Los Angeles Times": 2,
        "Bluesky: USA Today": 2,
        "Bluesky: The Economist": 2,
        "Bluesky: Liz Landers": 2,
        "Bluesky: Peter Baker": 2,
        "Bluesky: Edward Wong": 2,
        "Bluesky: Prashant Rao": 2,
        "Bluesky: The Connection": 2,
        "Bluesky: Robert Reid": 2,
        "Bluesky: Alex Panetta": 2,
        "Bluesky: Carol J Williams": 2,
        "Bluesky: Jacob Bogage": 2,
        "Bluesky: Brian Stelter": 2,
        "Bluesky: Asawin Suebsaeng": 2,
        "Bluesky: Nikki McCann Ramirez": 2,
        "Bluesky: Molly Redden": 2,
        "Bluesky: Ben Mullin": 2,
        "Bluesky: Erica Hellerstein": 2,
        "Bluesky: Ken Vogel": 2,
        "Bluesky: John Bresnahan": 2
      },
      "notes": "Disabled for now; wire sources remain inputs but this destination is not selected.",
      "destination_class": "mirror",
      "enabled": false
    },
    {
      "channel_key": "reuters",
      "minimum_score": 4,
      "priority": 20,
      "tag_boosts": {},
      "source_biases": {
        "Reuters": 6,
        "Bluesky: Reuters": 6
      },
      "notes": "Source-only channel; source gate is required before scoring. Source mirror; added after primary routing and never for skipped/no-match items.",
      "required_source_any": [
        "Reuters",
        "Bluesky: Reuters"
      ],
      "destination_class": "mirror",
      "required_source_ids": [
        "reuters"
      ],
      "required_source_classes": [
        "wire_service"
      ],
      "required_any": []
    },
    {
      "channel_key": "associated-press",
      "minimum_score": 4,
      "priority": 20,
      "tag_boosts": {},
      "source_biases": {
        "AP": 6,
        "Associated Press": 6,
        "Bluesky: AP": 6
      },
      "notes": "Source-only channel; source gate is required before scoring. Source mirror; added after primary routing and never for skipped/no-match items.",
      "required_source_any": [
        "Associated Press",
        "AP",
        "Bluesky: AP"
      ],
      "destination_class": "mirror",
      "required_source_ids": [
        "associated-press"
      ],
      "required_source_classes": [
        "wire_service"
      ],
      "required_any": []
    },
    {
      "channel_key": "nyt",
      "minimum_score": 4,
      "priority": 20,
      "tag_boosts": {},
      "source_biases": {
        "NYT": 6,
        "New York Times": 6,
        "Bluesky: New York Times": 6
      },
      "notes": "Source-only channel; source gate is required before scoring. Source mirror; added after primary routing and never for skipped/no-match items.",
      "required_source_any": [
        "NYT",
        "New York Times",
        "Bluesky: New York Times"
      ],
      "destination_class": "mirror",
      "required_source_ids": [
        "nyt"
      ],
      "required_source_classes": [
        "major_media"
      ],
      "required_any": []
    },
    {
      "channel_key": "wapo",
      "minimum_score": 4,
      "priority": 20,
      "tag_boosts": {},
      "source_biases": {
        "WaPo": 6,
        "Washington Post": 6,
        "Bluesky: Washington Post": 6
      },
      "notes": "Source-only channel; source gate is required before scoring. Source mirror; added after primary routing and never for skipped/no-match items.",
      "required_source_any": [
        "WaPo",
        "Washington Post",
        "Bluesky: Washington Post"
      ],
      "destination_class": "mirror",
      "required_source_ids": [
        "wapo"
      ],
      "required_source_classes": [
        "major_media"
      ],
      "required_any": []
    },
    {
      "channel_key": "abc-cbs-fox-nbc",
      "minimum_score": 4,
      "priority": 20,
      "tag_boosts": {},
      "source_biases": {
        "ABC": 6,
        "CBS": 6,
        "Fox": 6,
        "NBC": 6,
        "Bluesky: NBC News": 6,
        "Bluesky: CBS News": 6
      },
      "notes": "Source-only channel; source gate is required before scoring. Source mirror; added after primary routing and never for skipped/no-match items.",
      "required_source_any": [
        "ABC",
        "CBS",
        "Fox",
        "NBC",
        "Bluesky: NBC News",
        "Bluesky: CBS News"
      ],
      "destination_class": "mirror",
      "required_source_ids": [
        "abc",
        "cbs",
        "fox",
        "nbc"
      ],
      "required_source_classes": [
        "major_media"
      ],
      "required_any": []
    },
    {
      "channel_key": "newsweek",
      "minimum_score": 4,
      "priority": 20,
      "tag_boosts": {},
      "source_biases": {
        "Newsweek": 6,
        "Bluesky: Newsweek": 6
      },
      "notes": "Source-only channel; source gate is required before scoring. Source mirror; added after primary routing and never for skipped/no-match items.",
      "required_source_any": [
        "Newsweek",
        "Bluesky: Newsweek"
      ],
      "destination_class": "mirror",
      "required_source_ids": [
        "newsweek"
      ],
      "required_source_classes": [
        "major_media"
      ],
      "required_any": []
    },
    {
      "channel_key": "npr",
      "minimum_score": 4,
      "priority": 20,
      "tag_boosts": {},
      "source_biases": {
        "NPR": 6,
        "Bluesky: NPR": 6
      },
      "notes": "Source-only channel; source gate is required before scoring. Source mirror; added after primary routing and never for skipped/no-match items.",
      "required_source_any": [
        "NPR",
        "Bluesky: NPR"
      ],
      "destination_class": "mirror",
      "required_source_ids": [
        "npr"
      ],
      "required_source_classes": [
        "major_media"
      ],
      "required_any": []
    },
    {
      "channel_key": "the-hill",
      "priority": 65,
      "tag_boosts": {
        "government": 5,
        "legislation": 6,
        "election": 5,
        "sanctions": 2,
        "north_america": 1,
        "united_states": 1
      },
      "tag_penalties": {
        "latin_america": 6,
        "africa": 6,
        "middle_east": 5,
        "indo_pacific": 5,
        "europe": 3,
        "india": 8,
        "china": 5,
        "australia": 5
      },
      "term_penalties": {
        "vip_public_schedule": 8
      },
      "required_any": [
        "united_states",
        "north_america"
      ],
      "source_biases": {
        "Hill": 3,
        "Politico": 2,
        "Congress": 2,
        "Politics": 2,
        "Bluesky: Politico": 3,
        "Bluesky: The Hill": 3,
        "Bluesky: Liz Landers": 2,
        "Bluesky: Peter Baker": 2,
        "Bluesky: Jacob Bogage": 2,
        "Bluesky: Asawin Suebsaeng": 2,
        "Bluesky: Nikki McCann Ramirez": 2,
        "Bluesky: John Bresnahan": 3,
        "Bluesky: Ken Vogel": 3,
        "Bluesky: Anthony Adragna": 3
      },
      "minimum_score": 7,
      "destination_class": "primary"
    },
    {
      "channel_key": "the-white-house",
      "minimum_score": 4,
      "priority": 75,
      "term_boosts": {
        "presidential_nominations": 4
      },
      "tag_boosts": {
        "government": 5,
        "diplomacy": 4,
        "sanctions": 3,
        "official_alert": 5,
        "legislation": 2,
        "energy_security": 1
      },
      "tag_penalties": {
        "latin_america": 8,
        "africa": 8,
        "middle_east": 6,
        "indo_pacific": 6,
        "europe": 5
      },
      "required_any": [],
      "source_biases": {
        "White House": 6,
        "White House News": 6
      },
      "required_source_any": [
        "White House",
        "White House News"
      ],
      "notes": "Official White House channel only; State Department routes by country/region/topic.",
      "destination_class": "primary"
    },
    {
      "channel_key": "dept-of-war",
      "priority": 80,
      "tag_boosts": {
        "military": 5,
        "government": 3,
        "official_alert": 3,
        "military_organization": 2,
        "procurement": 1,
        "national_security": 2,
        "intelligence": 1,
        "homeland_security": 2,
        "command_control": 1
      },
      "tag_penalties": {
        "skip_candidate": 9,
        "cyber": 5,
        "indo_pacific": 7,
        "north_korea": 5,
        "china": 5,
        "middle_east": 8,
        "europe": 8,
        "iran": 6,
        "israel": 5,
        "lebanon": 5,
        "yemen": 5,
        "ukraine": 6,
        "russia": 6
      },
      "term_penalties": {
        "ukraine_war": 12,
        "iran_war": 12,
        "gaza_war": 8,
        "lebanon_conflict": 8,
        "presidential_nominations": 8,
        "centcom": 4,
        "strait_of_hormuz": 6,
        "bab_el_mandeb": 4
      },
      "required_any": [],
      "source_biases": {
        "Defense.gov": 6,
        "Department of Defense": 6,
        "DoD": 6,
        "DOD": 6,
        "Navy": 5,
        "Army": 5,
        "Air Force": 5,
        "Space Force": 5,
        "Marine Corps": 5,
        "Marines": 5,
        "DVIDS": 5,
        "CENTCOM": 5,
        "AFRICOM": 5,
        "EUCOM": 5,
        "INDOPACOM": 5,
        "NORTHCOM": 5,
        "SOUTHCOM": 5,
        "TRANSCOM": 5,
        "Department of Defense YouTube": 6
      },
      "required_source_any": [
        "Defense.gov",
        "Department of Defense",
        "DoD",
        "DOD",
        "Navy",
        "Army",
        "Air Force",
        "Space Force",
        "Marine Corps",
        "Marines",
        "DVIDS",
        "CENTCOM",
        "AFRICOM",
        "EUCOM",
        "INDOPACOM",
        "NORTHCOM",
        "SOUTHCOM",
        "TRANSCOM",
        "Fleet",
        "U.S. Army",
        "US Army",
        "USAF",
        "USMC",
        "USS ",
        "Department of Defense YouTube"
      ],
      "minimum_score": 4,
      "notes": "Official Defense Department and subordinate command/service content only. Source mirror; added after primary routing and never for skipped/no-match items.",
      "destination_class": "mirror",
      "required_source_classes": [
        "official_us_defense"
      ]
    },
    {
      "channel_key": "defense-media",
      "priority": 70,
      "tag_boosts": {
        "military": 4,
        "defense_industry": 3,
        "procurement": 2,
        "naval": 1,
        "air": 1,
        "ground": 1,
        "national_security": 2,
        "intelligence": 2,
        "command_control": 1,
        "isr": 1,
        "electronic_warfare": 1
      },
      "tag_penalties": {
        "skip_candidate": 9,
        "cyber": 5,
        "indo_pacific": 6,
        "north_korea": 4,
        "china": 4,
        "middle_east": 8,
        "europe": 8,
        "iran": 6,
        "israel": 4,
        "lebanon": 4,
        "yemen": 4,
        "ukraine": 6,
        "russia": 6
      },
      "term_penalties": {
        "ukraine_war": 12,
        "iran_war": 12,
        "gaza_war": 8,
        "lebanon_conflict": 8,
        "centcom": 3,
        "strait_of_hormuz": 6,
        "bab_el_mandeb": 3
      },
      "required_any": [
        "military",
        "defense_industry",
        "procurement",
        "naval",
        "air",
        "ground",
        "national_security",
        "intelligence",
        "command_control",
        "isr",
        "electronic_warfare"
      ],
      "source_biases": {
        "Defense": 3,
        "Breaking Defense": 3,
        "Bluesky: Bellingcat": 4,
        "Bluesky: Institute for the Study of War": 4,
        "Bluesky: Critical Threats Project": 4,
        "Bluesky: Jakub Janovsky": 3,
        "Bluesky: Covert Shores": 3,
        "Bluesky: War Mapper": 3,
        "Bluesky: Liveuamap": 3,
        "Bluesky: Faytuks Network": 3,
        "Bluesky: NOELREPORTS": 3,
        "Bellingcat": 4,
        "Institute for the Study of War": 4,
        "Critical Threats": 4,
        "War Mapper": 3,
        "Liveuamap": 3,
        "Faytuks": 3,
        "NOELREPORTS": 3,
        "Covert Shores": 3,
        "Bluesky: Natasha Bertrand": 3,
        "Bluesky: Paul McLeary": 3,
        "Bluesky: David Rohde": 3,
        "Bluesky: Anthony Adragna": 3,
        "Bluesky: Florian Flade": 3,
        "Bluesky: Vera Bergengruen": 3,
        "Bluesky: Sean Lyngaas": 2,
        "Bluesky: Tim Mak": 3,
        "Bluesky: Oz Katerji": 3,
        "Bluesky: WarTranslated": 4,
        "Bluesky: Tim Fernholz": 2,
        "Bluesky: Jennifer Hansler": 3,
        "Bluesky: Charlie Savage": 3,
        "Bluesky: The War Monitor": 4,
        "Bluesky: Euan MacDonald": 3,
        "Bluesky: Jim Bronskill": 3,
        "Bluesky: Drew FitzGerald": 3,
        "Bluesky: Kevin Knodell": 3,
        "Bluesky: Theresa Hitchens": 3,
        "Bluesky: Zach Rosenberg": 3,
        "Bluesky: Antoaneta Roussi": 3,
        "Bluesky: Alex Plitsas": 3,
        "Bluesky: Joby Warrick": 3,
        "Bluesky: Marisa Taylor": 2,
        "Bluesky: Eliot Higgins": 4,
        "Bluesky: Christiaan Triebert": 4,
        "Bluesky: Jake Godin": 4,
        "Bluesky: Shane Harris": 3,
        "Bluesky: Susan Glasser": 2,
        "Bluesky: Nahal Toosi": 3,
        "Bluesky: Ken Klippenstein": 2
      },
      "destination_class": "mirror",
      "required_source_classes": [
        "defense_media",
        "osint"
      ],
      "notes": " Source mirror; added after primary routing and never for skipped/no-match items."
    },
    {
      "channel_key": "think-tanks",
      "minimum_score": 4,
      "priority": 60,
      "tag_boosts": {
        "world": 1,
        "military": 2,
        "diplomacy": 3,
        "sanctions": 2,
        "defense_industry": 1,
        "national_security": 3,
        "intelligence": 2,
        "homeland_security": 2,
        "counterterrorism": 2
      },
      "tag_penalties": {
        "cyber": 4,
        "indo_pacific": 5,
        "north_korea": 3,
        "china": 3,
        "middle_east": 8,
        "europe": 8,
        "iran": 6,
        "israel": 3,
        "lebanon": 3,
        "yemen": 3,
        "ukraine": 6,
        "russia": 6
      },
      "term_penalties": {
        "ukraine_war": 12,
        "iran_war": 12,
        "gaza_war": 6,
        "lebanon_conflict": 6,
        "centcom": 3,
        "strait_of_hormuz": 6
      },
      "required_any": [],
      "source_biases": {
        "CSIS": 6,
        "RAND": 6,
        "Brookings": 6,
        "CFR": 6,
        "CNAS": 6,
        "Heritage Foundation": 6,
        "American Enterprise Institute": 6,
        "AEI": 6,
        "Hudson Institute": 6,
        "FDD": 6,
        "Stimson": 6,
        "IISS": 6,
        "Chatham House": 6,
        "IFRI": 6,
        "DGAP": 6,
        "ISW": 6,
        "RUSI": 6,
        "Atlantic Council": 6,
        "ASPI": 6,
        "International Crisis Group": 6
      },
      "notes": "Think-tank-produced content only; source gate is required before scoring. Source mirror; added after primary routing and never for skipped/no-match items.",
      "required_source_any": [
        "CSIS",
        "RAND",
        "Brookings",
        "CFR",
        "CNAS",
        "Heritage Foundation",
        "American Enterprise Institute",
        "AEI",
        "Hudson Institute",
        "FDD",
        "Stimson",
        "IISS",
        "Chatham House",
        "IFRI",
        "DGAP",
        "ISW",
        "RUSI",
        "Atlantic Council",
        "ASPI",
        "International Crisis Group"
      ],
      "destination_class": "mirror",
      "required_source_classes": [
        "think_tank"
      ]
    },
    {
      "channel_key": "review",
      "enabled": true,
      "destination_class": "review",
      "minimum_score": 0,
      "priority": 1000,
      "required_any": [],
      "tag_boosts": {},
      "notes": "Review-only destination for review_required and ambiguous articles."
    }
  ],
  "max_primary_destinations": 2
}
